pdf_generator/__init__.py
pdf_generator/angle.py
pdf_generator/from_html.py
pdf_generator/medias.py
pdf_generator/page_number.py
pdf_generator/pdf_generator.py
pdf_generator/styles.py
pdf_generator/table.py
pdf_generator/templates.py
pdf_generator-1.2.0.dist-info/LICENSE
pdf_generator-1.2.0.dist-info/WHEEL
pdf_generator-1.2.0.dist-info/METADATA
pdf_generator-1.2.0.dist-info/RECORD
