Metadata-Version: 2.1
Name: pdf-generator
Version: 1.2.0
Summary: PDF Generation utils
Author-email: Grégoire ROCHER <grgr@grgr.fr>
Requires-Python: >=3.7
Classifier: Programming Language :: Python :: 3
Classifier: Development Status :: 5 - Production/Stable
Requires-Dist: reportlab
